{
  "name" : "JSSCP Registration Form",
  "uuid" : "4b23dc0e-3ae0-4d41-8546-35797063e123",
  "formType" : "IndividualProfile",
  "formElementGroups" : [ {
    "uuid" : "2be450be-35db-47a6-a85e-5f1feb6f44cf",
    "name" : "Personal Details",
    "displayOrder" : 1.0,
    "display" : "Personal Details",
    "formElements" : [ {
      "name" : "Birth Order",
      "uuid" : "b0734413-8e47-4c4b-b53e-d5f21f41dd06",
      "keyValues" : [ ],
      "concept" : {
        "name" : "Birth Order",
        "uuid" : "821ba930-505c-4fd3-9f24-66b60ed45bac",
        "dataType" : "Numeric",
        "answers" : [ ],
        "active" : true
      },
      "displayOrder" : 1.0,
      "type" : "SingleSelect",
      "rule" : "'use strict';\n({params, imports}) => {\n  const individual = params.entity;\n  const formElement = params.formElement;\n  const statusBuilder = new imports.rulesConfig.FormElementStatusBuilder({individual, formElement});\n  statusBuilder.show().whenItem(individual.getAgeInYears()).lessThanOrEqualTo(3);\n  return statusBuilder.build();\n};",
      "mandatory" : true,
      "voided" : true
    }, {
      "name" : "Father's Name",
      "uuid" : "f798a48a-9d48-485e-a9f8-acba5a51c65e",
      "keyValues" : [ ],
      "concept" : {
        "name" : "Father's Name",
        "uuid" : "9e6983b8-06ef-4648-b360-6684100b1be1",
        "dataType" : "Text",
        "answers" : [ ],
        "active" : true
      },
      "displayOrder" : 2.0,
      "type" : "SingleSelect",
      "rule" : "'use strict';\n({params, imports}) => {\n  const individual = params.entity;\n  const formElement = params.formElement;\n  const statusBuilder = new imports.rulesConfig.FormElementStatusBuilder({individual, formElement});\n  statusBuilder.show().whenItem(individual.getAgeInYears()).lessThanOrEqualTo(3);\n  return statusBuilder.build();\n};",
      "mandatory" : true,
      "voided" : true
    }, {
      "name" : "Father's Occupation",
      "uuid" : "26e18485-b245-4394-8c63-eaf0f377d264",
      "keyValues" : [ ],
      "concept" : {
        "name" : "Father's Occupation",
        "uuid" : "bf564151-63f9-4176-917f-f37de34b9bae",
        "dataType" : "Coded",
        "answers" : [ {
          "name" : "Labour",
          "uuid" : "8ee4ddf3-34a4-4ec7-ac47-08498e8ef4a8",
          "dataType" : "NA",
          "answers" : [ ],
          "order" : 1.0,
          "active" : true
        }, {
          "name" : "Farming",
          "uuid" : "d06f8595-d126-4b6b-8305-ef7633892d75",
          "dataType" : "NA",
          "answers" : [ ],
          "order" : 2.0,
          "active" : true
        }, {
          "name" : "Don't know",
          "uuid" : "c483c8de-1e93-40e7-9e9a-dbe1c7e705a1",
          "dataType" : "NA",
          "answers" : [ ],
          "order" : 6.0,
          "active" : true
        }, {
          "name" : "Job",
          "uuid" : "27f77972-71d6-466c-94a3-214b4b4a23f6",
          "dataType" : "NA",
          "answers" : [ ],
          "order" : 4.0,
          "active" : true
        }, {
          "name" : "Business",
          "uuid" : "1e24aee4-fb61-4d60-b61a-cdde17e4545f",
          "dataType" : "NA",
          "answers" : [ ],
          "order" : 3.0,
          "active" : true
        }, {
          "name" : "Other",
          "uuid" : "798b7942-cf58-4d4e-a529-5972942e0a7e",
          "dataType" : "NA",
          "answers" : [ ],
          "order" : 5.0,
          "active" : true
        } ],
        "active" : true
      },
      "displayOrder" : 3.0,
      "type" : "SingleSelect",
      "rule" : "'use strict';\n({params, imports}) => {\n  const individual = params.entity;\n  const formElement = params.formElement;\n  const statusBuilder = new imports.rulesConfig.FormElementStatusBuilder({individual, formElement});\n  statusBuilder.show().whenItem(individual.getAgeInYears()).lessThanOrEqualTo(3);\n  return statusBuilder.build();\n};",
      "mandatory" : false,
      "voided" : true
    }, {
      "name" : "Father's Education",
      "uuid" : "aae9215b-306b-4ebb-96b4-5f8b5c721aad",
      "keyValues" : [ ],
      "concept" : {
        "name" : "Father's education Level",
        "uuid" : "b1001c4d-0449-464a-947f-a04c4fdcc651",
        "dataType" : "Coded",
        "answers" : [ {
          "name" : "Secondary",
          "uuid" : "279771f0-6d49-4fcc-bae9-9165c9775e96",
          "dataType" : "NA",
          "answers" : [ ],
          "order" : 2.0,
          "active" : true
        }, {
          "name" : "Graduate",
          "uuid" : "a9643c63-b5aa-422a-80fc-cf97893dd4bc",
          "dataType" : "NA",
          "answers" : [ ],
          "order" : 3.0,
          "active" : true
        }, {
          "name" : "Literate",
          "uuid" : "6d0924cf-3fa0-401d-a08c-9c0f85c3be6f",
          "dataType" : "NA",
          "answers" : [ ],
          "order" : 1.0,
          "active" : true
        }, {
          "name" : "Uneducated",
          "uuid" : "5ea8d117-730b-4047-a24a-03bbcfbc8a2f",
          "dataType" : "NA",
          "answers" : [ ],
          "order" : 5.0,
          "active" : true
        }, {
          "name" : "Primary",
          "uuid" : "bb825f03-51d4-4622-b977-e2893e76da70",
          "dataType" : "NA",
          "answers" : [ ],
          "order" : 6.0,
          "active" : true
        }, {
          "name" : "Post Graduate",
          "uuid" : "18915809-db25-474f-b245-5ceb3f26232f",
          "dataType" : "NA",
          "answers" : [ ],
          "order" : 4.0,
          "active" : true
        } ],
        "active" : true
      },
      "displayOrder" : 4.0,
      "type" : "SingleSelect",
      "rule" : "'use strict';\n({params, imports}) => {\n  const individual = params.entity;\n  const formElement = params.formElement;\n  const statusBuilder = new imports.rulesConfig.FormElementStatusBuilder({individual, formElement});\n  statusBuilder.show().whenItem(individual.getAgeInYears()).lessThanOrEqualTo(3);\n  return statusBuilder.build();\n};",
      "mandatory" : false,
      "voided" : true
    }, {
      "name" : "Mother's Name",
      "uuid" : "c57882fa-8719-40ae-9a49-928cb807dd81",
      "keyValues" : [ ],
      "concept" : {
        "name" : "Mother's Name",
        "uuid" : "74a554d8-5b87-4d27-9ae5-272ab326608f",
        "dataType" : "Text",
        "answers" : [ ],
        "active" : true
      },
      "displayOrder" : 5.0,
      "type" : "SingleSelect",
      "rule" : "'use strict';\n({params, imports}) => {\n  const individual = params.entity;\n  const formElement = params.formElement;\n  const statusBuilder = new imports.rulesConfig.FormElementStatusBuilder({individual, formElement});\n  statusBuilder.show().whenItem(individual.getAgeInYears()).lessThanOrEqualTo(3);\n  return statusBuilder.build();\n};",
      "mandatory" : true,
      "voided" : true
    }, {
      "name" : "Mother's Occupation",
      "uuid" : "76841378-f43d-4ccb-b4b8-6a7f634bb94e",
      "keyValues" : [ ],
      "concept" : {
        "name" : "Mother's Occupation",
        "uuid" : "ea760e4f-c12f-490b-9865-9c6e4510ce64",
        "dataType" : "Coded",
        "answers" : [ {
          "name" : "Farming",
          "uuid" : "d06f8595-d126-4b6b-8305-ef7633892d75",
          "dataType" : "NA",
          "answers" : [ ],
          "order" : 3.0,
          "active" : true
        }, {
          "name" : "Job",
          "uuid" : "27f77972-71d6-466c-94a3-214b4b4a23f6",
          "dataType" : "NA",
          "answers" : [ ],
          "order" : 5.0,
          "active" : true
        }, {
          "name" : "Business",
          "uuid" : "1e24aee4-fb61-4d60-b61a-cdde17e4545f",
          "dataType" : "NA",
          "answers" : [ ],
          "order" : 4.0,
          "active" : true
        }, {
          "name" : "Labour",
          "uuid" : "8ee4ddf3-34a4-4ec7-ac47-08498e8ef4a8",
          "dataType" : "NA",
          "answers" : [ ],
          "order" : 2.0,
          "active" : true
        }, {
          "name" : "Don't know",
          "uuid" : "c483c8de-1e93-40e7-9e9a-dbe1c7e705a1",
          "dataType" : "NA",
          "answers" : [ ],
          "order" : 7.0,
          "active" : true
        }, {
          "name" : "Housework",
          "uuid" : "d7d45e44-8ce9-42d4-a98e-78d11c58d899",
          "dataType" : "NA",
          "answers" : [ ],
          "order" : 1.0,
          "active" : true
        }, {
          "name" : "Other",
          "uuid" : "798b7942-cf58-4d4e-a529-5972942e0a7e",
          "dataType" : "NA",
          "answers" : [ ],
          "order" : 6.0,
          "active" : true
        } ],
        "active" : true
      },
      "displayOrder" : 6.0,
      "type" : "SingleSelect",
      "rule" : "'use strict';\n({params, imports}) => {\n  const individual = params.entity;\n  const formElement = params.formElement;\n  const statusBuilder = new imports.rulesConfig.FormElementStatusBuilder({individual, formElement});\n  statusBuilder.show().whenItem(individual.getAgeInYears()).lessThanOrEqualTo(3);\n  return statusBuilder.build();\n};",
      "mandatory" : false,
      "voided" : true
    }, {
      "name" : "Mother's Education",
      "uuid" : "afa9c6d4-cfe5-4551-83b8-159cd8b62846",
      "keyValues" : [ ],
      "concept" : {
        "name" : "Mother's education Level",
        "uuid" : "d98aae1a-ce33-4e51-b031-66e13bc0ba11",
        "dataType" : "Coded",
        "answers" : [ {
          "name" : "Post Graduate",
          "uuid" : "18915809-db25-474f-b245-5ceb3f26232f",
          "dataType" : "NA",
          "answers" : [ ],
          "order" : 4.0,
          "active" : true
        }, {
          "name" : "Graduate",
          "uuid" : "a9643c63-b5aa-422a-80fc-cf97893dd4bc",
          "dataType" : "NA",
          "answers" : [ ],
          "order" : 3.0,
          "active" : true
        }, {
          "name" : "Primary",
          "uuid" : "bb825f03-51d4-4622-b977-e2893e76da70",
          "dataType" : "NA",
          "answers" : [ ],
          "order" : 6.0,
          "active" : true
        }, {
          "name" : "Secondary",
          "uuid" : "279771f0-6d49-4fcc-bae9-9165c9775e96",
          "dataType" : "NA",
          "answers" : [ ],
          "order" : 2.0,
          "active" : true
        }, {
          "name" : "Uneducated",
          "uuid" : "5ea8d117-730b-4047-a24a-03bbcfbc8a2f",
          "dataType" : "NA",
          "answers" : [ ],
          "order" : 5.0,
          "active" : true
        }, {
          "name" : "Literate",
          "uuid" : "6d0924cf-3fa0-401d-a08c-9c0f85c3be6f",
          "dataType" : "NA",
          "answers" : [ ],
          "order" : 1.0,
          "active" : true
        } ],
        "active" : true
      },
      "displayOrder" : 7.0,
      "type" : "SingleSelect",
      "rule" : "'use strict';\n({params, imports}) => {\n  const individual = params.entity;\n  const formElement = params.formElement;\n  const statusBuilder = new imports.rulesConfig.FormElementStatusBuilder({individual, formElement});\n  statusBuilder.show().whenItem(individual.getAgeInYears()).lessThanOrEqualTo(3);\n  return statusBuilder.build();\n};",
      "mandatory" : false,
      "voided" : true
    }, {
      "name" : "Religion",
      "uuid" : "bd2eb2fc-1d7e-4512-a6f6-6fc9c10a4c61",
      "keyValues" : [ ],
      "concept" : {
        "name" : "Religion",
        "uuid" : "b2c60cb8-983c-4e0e-a90d-4b21e87e10bd",
        "dataType" : "Coded",
        "answers" : [ {
          "name" : "Hindu",
          "uuid" : "6dbd4a89-d040-4ed3-bf1d-23bafdb1553e",
          "dataType" : "NA",
          "answers" : [ ],
          "order" : 1.0,
          "active" : true
        }, {
          "name" : "Sikh",
          "uuid" : "2f6e7ba7-15dc-4af3-b4d7-e971e6733525",
          "dataType" : "NA",
          "answers" : [ ],
          "order" : 4.0,
          "active" : true
        }, {
          "name" : "Jain",
          "uuid" : "e8bb7929-2357-49ff-8c98-28b338f2c6d8",
          "dataType" : "NA",
          "answers" : [ ],
          "order" : 5.0,
          "active" : true
        }, {
          "name" : "Muslim",
          "uuid" : "fd46c9f7-783a-4cc0-b6b3-489aeb28f26c",
          "dataType" : "NA",
          "answers" : [ ],
          "order" : 2.0,
          "active" : true
        }, {
          "name" : "Christian",
          "uuid" : "a1a0ecc3-2a85-43c4-b75a-3544a1ada0bf",
          "dataType" : "NA",
          "answers" : [ ],
          "order" : 3.0,
          "active" : true
        }, {
          "name" : "Other",
          "uuid" : "798b7942-cf58-4d4e-a529-5972942e0a7e",
          "dataType" : "NA",
          "answers" : [ ],
          "order" : 6.0,
          "active" : true
        } ],
        "active" : true
      },
      "displayOrder" : 8.0,
      "type" : "SingleSelect",
      "mandatory" : true,
      "voided" : true
    }, {
      "name" : "Caste",
      "uuid" : "f2d5671d-85ac-4307-891f-281ea0eca37c",
      "keyValues" : [ ],
      "concept" : {
        "name" : "Caste Category",
        "uuid" : "9ad4b520-4e33-4b1b-a056-37ae6418988f",
        "dataType" : "Coded",
        "answers" : [ {
          "name" : "General",
          "uuid" : "9b3a3dca-b93a-4b67-975f-5f6f1a815cea",
          "dataType" : "NA",
          "answers" : [ ],
          "order" : 4.0,
          "active" : true
        }, {
          "name" : "SC",
          "uuid" : "0b78a94a-c652-4d59-ad16-c9138db05e29",
          "dataType" : "NA",
          "answers" : [ ],
          "order" : 2.0,
          "active" : true
        }, {
          "name" : "ST",
          "uuid" : "8d1c99b2-fbed-4407-9f6a-040b9a5731b2",
          "dataType" : "NA",
          "answers" : [ ],
          "order" : 1.0,
          "active" : true
        }, {
          "name" : "OBC",
          "uuid" : "8aa7b5ea-5d35-4a08-af33-0345af903e2f",
          "dataType" : "NA",
          "answers" : [ ],
          "order" : 3.0,
          "active" : true
        } ],
        "active" : true
      },
      "displayOrder" : 9.0,
      "type" : "SingleSelect",
      "mandatory" : false,
      "voided" : true
    }, {
      "name" : "Sub caste",
      "uuid" : "e14987bd-1959-47b0-9c99-9c4daefddc76",
      "keyValues" : [ ],
      "concept" : {
        "name" : "Sub Caste",
        "uuid" : "047877ac-dba7-4acf-8c77-97c979c2fc26",
        "dataType" : "Coded",
        "answers" : [ {
          "name" : "Porte",
          "uuid" : "7473f572-0116-46fe-a5ad-fd56317598a2",
          "dataType" : "NA",
          "answers" : [ ],
          "order" : 1.0,
          "active" : true
        }, {
          "name" : "Maravi",
          "uuid" : "1ddf20cd-1bdc-4711-9c57-f73aa71b4d3b",
          "dataType" : "NA",
          "answers" : [ ],
          "order" : 16.0,
          "active" : true
        }, {
          "name" : "Oraon",
          "uuid" : "0bebd451-d11f-404e-9207-6bd189eb83cf",
          "dataType" : "NA",
          "answers" : [ ],
          "order" : 3.0,
          "active" : true
        }, {
          "name" : "Kaivart",
          "uuid" : "bdbec003-f5dc-4274-b1cb-fbfc0c97308e",
          "dataType" : "NA",
          "answers" : [ ],
          "order" : 13.0,
          "active" : true
        }, {
          "name" : "Devangan",
          "uuid" : "a4355798-1072-491f-b60f-c19feeb39188",
          "dataType" : "NA",
          "answers" : [ ],
          "order" : 11.0,
          "active" : true
        }, {
          "name" : "Satnami",
          "uuid" : "38e6aaf2-d6cd-4a7b-9087-4bdc3df31ece",
          "dataType" : "NA",
          "answers" : [ ],
          "order" : 6.0,
          "active" : true
        }, {
          "name" : "Bhanu",
          "uuid" : "63ea0e4b-f637-43aa-a4b9-7f5c164d12d8",
          "dataType" : "NA",
          "answers" : [ ],
          "order" : 26.0,
          "active" : true
        }, {
          "name" : "DHanuhar",
          "uuid" : "66c75ba6-fb03-43e2-b992-213d396dbcd5",
          "dataType" : "NA",
          "answers" : [ ],
          "order" : 10.0,
          "active" : true
        }, {
          "name" : "Sakat",
          "uuid" : "d3de0ad3-909d-4d2e-9de5-cf72445d4484",
          "dataType" : "NA",
          "answers" : [ ],
          "order" : 29.0,
          "active" : true
        }, {
          "name" : "Gandharv",
          "uuid" : "3aba04d1-0bea-4d80-88da-b220a9064170",
          "dataType" : "NA",
          "answers" : [ ],
          "order" : 2.0,
          "active" : true
        }, {
          "name" : "Prajapati",
          "uuid" : "9a5240ee-7d93-4413-ae0a-60bd9cd78b31",
          "dataType" : "NA",
          "answers" : [ ],
          "order" : 18.0,
          "active" : true
        }, {
          "name" : "Marar",
          "uuid" : "ac63f895-de9a-4551-9d4e-8f73688bcda4",
          "dataType" : "NA",
          "answers" : [ ],
          "order" : 28.0,
          "active" : true
        }, {
          "name" : "Vishwakarma",
          "uuid" : "959045fe-3dce-40fc-b1e2-a162f2a777bd",
          "dataType" : "NA",
          "answers" : [ ],
          "order" : 24.0,
          "active" : true
        }, {
          "name" : "Baiga",
          "uuid" : "2b90b234-8a63-4d4c-92d0-6389d8b1fb78",
          "dataType" : "NA",
          "answers" : [ ],
          "order" : 19.0,
          "active" : true
        }, {
          "name" : "Manikpuri",
          "uuid" : "c14b8aa4-2fba-4c45-a544-367940a3031f",
          "dataType" : "NA",
          "answers" : [ ],
          "order" : 4.0,
          "active" : true
        }, {
          "name" : "Khusaro",
          "uuid" : "2cdc0f0e-bf32-4d85-b48a-c14379b2f8f1",
          "dataType" : "NA",
          "answers" : [ ],
          "order" : 15.0,
          "active" : true
        }, {
          "name" : "Bhaina",
          "uuid" : "8684971e-9d09-4faa-8183-74a0505e7f5c",
          "dataType" : "NA",
          "answers" : [ ],
          "order" : 9.0,
          "active" : true
        }, {
          "name" : "Kanvar",
          "uuid" : "e84a706e-e04d-4ea5-9f39-ab33a2c0ceba",
          "dataType" : "NA",
          "answers" : [ ],
          "order" : 14.0,
          "active" : true
        }, {
          "name" : "Rajak",
          "uuid" : "1062d52b-5b2c-4bd8-8165-ac4a3a9e11d4",
          "dataType" : "NA",
          "answers" : [ ],
          "order" : 17.0,
          "active" : true
        }, {
          "name" : "Dhruv",
          "uuid" : "e5ea06c5-146b-4944-85ed-a9cfa43c4b58",
          "dataType" : "NA",
          "answers" : [ ],
          "order" : 12.0,
          "active" : true
        }, {
          "name" : "Gond",
          "uuid" : "7335b4a6-fd22-4061-ba4f-54c5f3d1bfbe",
          "dataType" : "NA",
          "answers" : [ ],
          "order" : 20.0,
          "active" : true
        }, {
          "name" : "Panika",
          "uuid" : "5718df2e-2311-42ad-88b6-c2d7be74df22",
          "dataType" : "NA",
          "answers" : [ ],
          "order" : 21.0,
          "active" : true
        }, {
          "name" : "Urav",
          "uuid" : "5d839be5-7013-450f-b986-a8b95669897c",
          "dataType" : "NA",
          "answers" : [ ],
          "order" : 32.0,
          "active" : true
        }, {
          "name" : "Yadav",
          "uuid" : "65b5abfa-9229-48bf-8ed7-40e715840302",
          "dataType" : "NA",
          "answers" : [ ],
          "order" : 22.0,
          "active" : true
        }, {
          "name" : "Sidar",
          "uuid" : "86ac2f19-2f17-425b-a593-cc91c968d5d2",
          "dataType" : "NA",
          "answers" : [ ],
          "order" : 31.0,
          "active" : true
        }, {
          "name" : "Other",
          "uuid" : "798b7942-cf58-4d4e-a529-5972942e0a7e",
          "dataType" : "NA",
          "answers" : [ ],
          "order" : 25.0,
          "unique" : true,
          "active" : true
        }, {
          "name" : "Dhurve",
          "uuid" : "5c4838cf-67e5-400a-8c4d-03cd1fcd6a92",
          "dataType" : "NA",
          "answers" : [ ],
          "order" : 0.0,
          "active" : true
        }, {
          "name" : "Sauta",
          "uuid" : "3a9cd092-ed29-4bfa-959d-f3a1500ffd1b",
          "dataType" : "NA",
          "answers" : [ ],
          "order" : 30.0,
          "active" : true
        }, {
          "name" : "Nayak",
          "uuid" : "a27ce1dc-59de-4b83-a25c-4672013530f5",
          "dataType" : "NA",
          "answers" : [ ],
          "order" : 23.0,
          "active" : true
        }, {
          "name" : "Patel",
          "uuid" : "0e03a56d-dfca-4365-b10b-d1bc8390ff87",
          "dataType" : "NA",
          "answers" : [ ],
          "order" : 7.0,
          "active" : true
        }, {
          "name" : "Jaiswal",
          "uuid" : "e19af6c6-f875-4c30-af2f-5b9cd9043bbd",
          "dataType" : "NA",
          "answers" : [ ],
          "order" : 8.0,
          "active" : true
        }, {
          "name" : "Kol",
          "uuid" : "524076aa-e018-4a34-a1ad-d95a21896c37",
          "dataType" : "NA",
          "answers" : [ ],
          "order" : 27.0,
          "active" : true
        }, {
          "name" : "Markam",
          "uuid" : "8f5e9c30-8b1c-422d-86f2-dba92e8e6856",
          "dataType" : "NA",
          "answers" : [ ],
          "order" : 5.0,
          "active" : true
        } ],
        "active" : true
      },
      "displayOrder" : 10.0,
      "type" : "SingleSelect",
      "mandatory" : false,
      "voided" : true
    }, {
      "name" : "Other sub caste (please specify)",
      "uuid" : "1797426a-2960-42cf-9e21-325a7d4ff671",
      "keyValues" : [ ],
      "concept" : {
        "name" : "Other sub caste",
        "uuid" : "ae7d54e9-fac0-4898-b334-87664bd055d2",
        "dataType" : "Text",
        "answers" : [ ],
        "active" : true
      },
      "displayOrder" : 11.0,
      "type" : "SingleSelect",
      "rule" : "'use strict';\n({params, imports}) => {\n  const individual = params.entity;\n  const formElement = params.formElement;\n  const statusBuilder = new imports.rulesConfig.FormElementStatusBuilder({individual, formElement});\n  statusBuilder.show().when.valueInRegistration(\"Sub caste\")\n            .containsAnswerConceptName(\"Other\");\n  return statusBuilder.build();\n};",
      "mandatory" : true,
      "voided" : true
    } ],
    "voided" : true,
    "timed" : false
  }, {
    "uuid" : "ca39681e-b89e-420f-a72e-3e8527518b78",
    "name" : "Individual information",
    "displayOrder" : 2.0,
    "display" : "Individual information",
    "formElements" : [ {
      "name" : "Relation to head of the household",
      "uuid" : "24a04cdd-ec5f-4e61-a611-6ead7557bbd7",
      "keyValues" : [ ],
      "concept" : {
        "name" : "Relation to head of the household",
        "uuid" : "eaee156e-8ef3-4148-a80c-a466cd059ae3",
        "dataType" : "Coded",
        "answers" : [ {
          "name" : "Sister",
          "uuid" : "8e131779-ed2b-4db9-a217-529aef1c1562",
          "dataType" : "NA",
          "answers" : [ ],
          "order" : 6.0,
          "active" : true
        }, {
          "name" : "Wife",
          "uuid" : "dd3958f6-376a-447a-90cd-95ed2c8cdf18",
          "dataType" : "NA",
          "answers" : [ ],
          "order" : 1.0,
          "active" : true
        }, {
          "name" : "Self",
          "uuid" : "03c3c21c-6e8c-4210-a15e-fbb181c266b9",
          "dataType" : "NA",
          "answers" : [ ],
          "order" : 0.0,
          "active" : true
        }, {
          "name" : "Daughter",
          "uuid" : "0f8b507f-709f-44af-855b-67b2f8b8a800",
          "dataType" : "NA",
          "answers" : [ ],
          "order" : 4.0,
          "active" : true
        }, {
          "name" : "Son",
          "uuid" : "cb3de879-6c0a-497b-81ad-d825a5740daa",
          "dataType" : "NA",
          "answers" : [ ],
          "order" : 3.0,
          "active" : true
        }, {
          "name" : "Grandfather",
          "uuid" : "9840eeaf-befa-48cf-8c4e-441bdb982e02",
          "dataType" : "NA",
          "answers" : [ ],
          "order" : 9.0,
          "active" : true
        }, {
          "name" : "Brother",
          "uuid" : "53df677a-7d97-48d7-a644-38e4132c7076",
          "dataType" : "NA",
          "answers" : [ ],
          "order" : 5.0,
          "active" : true
        }, {
          "name" : "Sister in law",
          "uuid" : "9bc82780-fa25-4350-8288-86c4be3b0ebf",
          "dataType" : "NA",
          "answers" : [ ],
          "order" : 8.0,
          "active" : true
        }, {
          "name" : "Grandmother",
          "uuid" : "a03e8eab-7173-4876-86e6-22be1e261f86",
          "dataType" : "NA",
          "answers" : [ ],
          "order" : 10.0,
          "active" : true
        }, {
          "name" : "Other",
          "uuid" : "798b7942-cf58-4d4e-a529-5972942e0a7e",
          "dataType" : "NA",
          "answers" : [ ],
          "order" : 11.0,
          "active" : true
        }, {
          "name" : "Brother in law",
          "uuid" : "96163c7e-00a7-4b7c-bc65-a6880115bded",
          "dataType" : "NA",
          "answers" : [ ],
          "order" : 7.0,
          "active" : true
        }, {
          "name" : "Husband",
          "uuid" : "df321e20-e432-40c9-bdf1-a874efe0a7d6",
          "dataType" : "NA",
          "answers" : [ ],
          "order" : 2.0,
          "active" : true
        } ],
        "active" : true,
        "keyValues" : [ ]
      },
      "displayOrder" : 1.0,
      "type" : "SingleSelect",
      "mandatory" : true,
      "voided" : true
    }, {
      "name" : "Non programme village name",
      "uuid" : "baade36e-0b91-4e9e-ae34-2e499564d8f9",
      "keyValues" : [ ],
      "concept" : {
        "name" : "Non programme village name",
        "uuid" : "1c710642-4f37-4f47-9df9-393127eaafc9",
        "dataType" : "Text",
        "answers" : [ ],
        "active" : true
      },
      "displayOrder" : 2.0,
      "type" : "SingleSelect",
      "rule" : "'use strict';\n({params, imports}) => {\n  const _ = imports.lodash;\n  const individual = params.entity;\n  const formElement = params.formElement;\n  const statusBuilder = new imports.rulesConfig.FormElementStatusBuilder({individual, formElement});\n \n  const showCondition = _.isEqual(individual.lowestAddressLevel.name,'Non programme village');\n    statusBuilder.show().whenItem(showCondition).is.truthy;\n   return statusBuilder.build();\n};",
      "mandatory" : true
    }, {
      "name" : "Father/Husband's Name",
      "uuid" : "32db1eb9-2ad0-4c65-8a90-6393f5a35831",
      "keyValues" : [ ],
      "concept" : {
        "name" : "Father/Husband's Name",
        "uuid" : "ecdf3c54-2808-494d-87be-8fb744d5c3bc",
        "dataType" : "Text",
        "answers" : [ ],
        "active" : true
      },
      "displayOrder" : 3.0,
      "type" : "SingleSelect",
      "mandatory" : true
    }, {
      "name" : "Marital status",
      "uuid" : "a0d08992-5581-49e8-ba18-66b0e37341ef",
      "keyValues" : [ ],
      "concept" : {
        "name" : "Marital status",
        "uuid" : "9e995ea6-a5f7-410f-adc2-2d2ce6d5e19b",
        "dataType" : "Coded",
        "answers" : [ {
          "name" : "Currently married",
          "uuid" : "ba48e389-23df-43e4-89a6-85f392d4312e",
          "dataType" : "NA",
          "answers" : [ ],
          "order" : 0.0,
          "active" : true
        }, {
          "name" : "Separated",
          "uuid" : "568a29bd-40fc-4261-bb85-9f9366b9be1b",
          "dataType" : "NA",
          "answers" : [ ],
          "order" : 2.0,
          "active" : true
        }, {
          "name" : "Divorced",
          "uuid" : "1bc8befa-49b7-4a70-8203-8ec5d0660783",
          "dataType" : "NA",
          "answers" : [ ],
          "order" : 3.0,
          "active" : true
        }, {
          "name" : "Remarried",
          "uuid" : "c219f819-db31-4a13-a895-fe67155e284b",
          "dataType" : "NA",
          "answers" : [ ],
          "order" : 5.0,
          "active" : true
        }, {
          "name" : "Other",
          "uuid" : "798b7942-cf58-4d4e-a529-5972942e0a7e",
          "dataType" : "NA",
          "answers" : [ ],
          "order" : 6.0,
          "active" : true
        }, {
          "name" : "Widow(er)",
          "uuid" : "9329d91a-385b-4633-a788-c10ccb7d1143",
          "dataType" : "NA",
          "answers" : [ ],
          "order" : 4.0,
          "active" : true
        }, {
          "name" : "Unmarried",
          "uuid" : "4a4cc0eb-25c0-47b8-b9dd-de2dbefc1425",
          "dataType" : "NA",
          "answers" : [ ],
          "order" : 1.0,
          "active" : true
        } ],
        "active" : true
      },
      "displayOrder" : 4.0,
      "type" : "SingleSelect",
      "rule" : "'use strict';\n({params, imports}) => {\n  const individual = params.entity;\n  const formElement = params.formElement;\n  const statusBuilder = new imports.rulesConfig.FormElementStatusBuilder({individual, formElement});\n  statusBuilder.show().whenItem(individual.getAgeInYears()).is.greaterThanOrEqualTo(16);\n  return statusBuilder.build();\n};",
      "mandatory" : true
    }, {
      "name" : "Date of marriage",
      "uuid" : "e6972f41-f35d-4511-b984-2c9b598bd793",
      "keyValues" : [ ],
      "concept" : {
        "name" : "Date of marriage",
        "uuid" : "9d958124-09bb-466c-a4b4-db8d285def1f",
        "dataType" : "Date",
        "answers" : [ ],
        "active" : true
      },
      "displayOrder" : 5.0,
      "type" : "SingleSelect",
      "rule" : "'use strict';\n({params, imports}) => {\n  const individual = params.entity;\n  const formElement = params.formElement;\n  const statusBuilder = new imports.rulesConfig.FormElementStatusBuilder({individual, formElement});\n  statusBuilder.show().whenItem(individual.getAgeInYears()).is.greaterThanOrEqualTo(16).\n  and.when.valueInRegistration('Marital status').containsAnswerConceptNameOtherThan('Unmarried');\n  return statusBuilder.build();\n};",
      "mandatory" : false
    }, {
      "name" : "Education",
      "uuid" : "bd8587a8-e84d-4a55-a46e-e7bf2290df68",
      "keyValues" : [ ],
      "concept" : {
        "name" : "Education",
        "uuid" : "673d65bd-6dc4-4aac-8e1e-1ee355ac081b",
        "dataType" : "Coded",
        "answers" : [ {
          "name" : "8-10",
          "uuid" : "6b941c49-349f-40f6-a4ae-bdd00f45fbba",
          "dataType" : "NA",
          "answers" : [ ],
          "order" : 4.0,
          "active" : true
        }, {
          "name" : "Graduation",
          "uuid" : "ff7c5cd7-fe19-4a64-b8cb-700b4ad7a58f",
          "dataType" : "NA",
          "answers" : [ ],
          "order" : 6.0,
          "active" : true
        }, {
          "name" : "Illiterate",
          "uuid" : "45b68efb-635d-48ae-9fdf-64f0ea3f46db",
          "dataType" : "NA",
          "answers" : [ ],
          "order" : 0.0,
          "active" : true
        }, {
          "name" : "11-12",
          "uuid" : "d3ff5645-4c84-47f4-9f35-6d0242cd727c",
          "dataType" : "NA",
          "answers" : [ ],
          "order" : 5.0,
          "active" : true
        }, {
          "name" : "NA",
          "uuid" : "7efbfba4-66d1-4510-9024-aaaedf439392",
          "dataType" : "NA",
          "answers" : [ ],
          "order" : 8.0,
          "active" : true
        }, {
          "name" : "Post Graduation and above",
          "uuid" : "4c9f0571-a3ce-4026-854e-a28b388b0c0f",
          "dataType" : "NA",
          "answers" : [ ],
          "order" : 7.0,
          "active" : true
        }, {
          "name" : "6-7",
          "uuid" : "0b2b6bb5-7eb8-4b14-bc68-662fade3aca4",
          "dataType" : "NA",
          "answers" : [ ],
          "order" : 3.0,
          "active" : true
        }, {
          "name" : "Literate without schooling",
          "uuid" : "9fa90cc8-0dc0-43ee-820f-39f8fe3ca1ec",
          "dataType" : "NA",
          "answers" : [ ],
          "order" : 1.0,
          "active" : true
        }, {
          "name" : "1-5",
          "uuid" : "9ac76826-0daa-4b90-9a9c-e269ac168005",
          "dataType" : "NA",
          "answers" : [ ],
          "order" : 2.0,
          "active" : true
        } ],
        "active" : true
      },
      "displayOrder" : 6.0,
      "type" : "SingleSelect",
      "rule" : "",
      "mandatory" : true
    }, {
      "name" : "Occupation",
      "uuid" : "d54f2ad3-359e-4de8-813f-c37dd1c6b9b5",
      "keyValues" : [ ],
      "concept" : {
        "name" : "Occupation",
        "uuid" : "20ef261a-f110-4eaa-a592-2a1eeb0bf061",
        "dataType" : "Coded",
        "answers" : [ {
          "name" : "Professional/Technical",
          "uuid" : "2a5dc992-7a1e-4fb2-9a9d-3093f7c9fca3",
          "dataType" : "NA",
          "answers" : [ ],
          "order" : 4.0,
          "active" : true
        }, {
          "name" : "NA",
          "uuid" : "7efbfba4-66d1-4510-9024-aaaedf439392",
          "dataType" : "NA",
          "answers" : [ ],
          "order" : 12.0,
          "active" : true
        }, {
          "name" : "Farmer",
          "uuid" : "f021800c-b3f5-4c70-b90a-dcbb83227b55",
          "dataType" : "NA",
          "answers" : [ ],
          "order" : 1.0,
          "active" : true
        }, {
          "name" : "Unemployed",
          "uuid" : "fc63152f-457d-4392-aa80-87e6fd19f20a",
          "dataType" : "NA",
          "answers" : [ ],
          "order" : 0.0,
          "active" : true
        }, {
          "name" : "Shopkeeper",
          "uuid" : "4a13e345-7d13-4649-a370-1722a596d0fe",
          "dataType" : "NA",
          "answers" : [ ],
          "order" : 5.0,
          "active" : true
        }, {
          "name" : "Other",
          "uuid" : "798b7942-cf58-4d4e-a529-5972942e0a7e",
          "dataType" : "NA",
          "answers" : [ ],
          "order" : 11.0,
          "active" : true
        }, {
          "name" : "Skilled manual",
          "uuid" : "84000e44-81ea-425f-8c88-9e4b111a5570",
          "dataType" : "NA",
          "answers" : [ ],
          "order" : 3.0,
          "active" : true
        }, {
          "name" : "Housework",
          "uuid" : "d7d45e44-8ce9-42d4-a98e-78d11c58d899",
          "dataType" : "NA",
          "answers" : [ ],
          "order" : 10.0,
          "active" : true
        }, {
          "name" : "Government Job",
          "uuid" : "fd6a3706-f1f3-4f86-96a3-80b6866612a2",
          "dataType" : "NA",
          "answers" : [ ],
          "order" : 6.0,
          "active" : true
        }, {
          "name" : "Private Job",
          "uuid" : "0bef903a-20e5-4efa-940a-37d419f68f7c",
          "dataType" : "NA",
          "answers" : [ ],
          "order" : 7.0,
          "active" : true
        }, {
          "name" : "Daily wage labourer",
          "uuid" : "1100010c-b1fe-4d14-a2ec-c46a8af3cbb1",
          "dataType" : "NA",
          "answers" : [ ],
          "order" : 2.0,
          "active" : true
        } ],
        "active" : true
      },
      "displayOrder" : 7.0,
      "type" : "SingleSelect",
      "rule" : "",
      "mandatory" : true
    }, {
      "name" : "Specify the other occupation",
      "uuid" : "d2d716b5-0c4b-47a7-a93c-a2710dc54c78",
      "keyValues" : [ ],
      "concept" : {
        "name" : "Other occupation",
        "uuid" : "4c429211-634e-4c2b-9a31-3f0a395f8f8d",
        "dataType" : "Text",
        "answers" : [ ],
        "active" : true
      },
      "displayOrder" : 8.0,
      "type" : "SingleSelect",
      "rule" : "'use strict';\n({params, imports}) => {\n  const individual = params.entity;\n  const formElement = params.formElement;\n  const statusBuilder = new imports.rulesConfig.FormElementStatusBuilder({individual, formElement});\n  statusBuilder.show().valueInRegistration(\"Occupation\").containsAnswerConceptName('Other');\n  return statusBuilder.build();\n};",
      "mandatory" : false
    }, {
      "name" : "Is sterlization operation done?",
      "uuid" : "25a8fd3d-2f78-43ab-88b5-2bc0cd0c91dd",
      "keyValues" : [ ],
      "concept" : {
        "name" : "Is sterlization operation done?",
        "uuid" : "852f4e54-4969-4724-94e0-cddef0ac1f66",
        "dataType" : "Coded",
        "answers" : [ {
          "name" : "Yes",
          "uuid" : "57e20de7-10de-4391-b7ce-87b2f40d19a2",
          "dataType" : "NA",
          "answers" : [ ],
          "order" : 0.0,
          "active" : true
        }, {
          "name" : "No",
          "uuid" : "f88da2e8-6ab4-44b5-b762-233485cd25f9",
          "dataType" : "NA",
          "answers" : [ ],
          "order" : 1.0,
          "active" : true
        } ],
        "active" : true,
        "keyValues" : [ ]
      },
      "displayOrder" : 9.0,
      "type" : "SingleSelect",
      "rule" : "'use strict';\n({params, imports}) => {\n  const individual = params.entity;\n  const formElement = params.formElement;\n  const statusBuilder = new imports.rulesConfig.FormElementStatusBuilder({individual, formElement});\n  statusBuilder.show().whenItem(individual.getAgeInYears()).is.greaterThanOrEqualTo(16);\n  return statusBuilder.build();\n};",
      "mandatory" : true,
      "voided" : true
    }, {
      "name" : "Whether any disability",
      "uuid" : "41fb3d1d-55bb-4fbd-b1b4-45b112258be3",
      "keyValues" : [ ],
      "concept" : {
        "name" : "Whether any disability",
        "uuid" : "bab107f6-fc0e-4be7-ab71-658a92d72f35",
        "dataType" : "Coded",
        "answers" : [ {
          "name" : "Yes",
          "uuid" : "57e20de7-10de-4391-b7ce-87b2f40d19a2",
          "dataType" : "NA",
          "answers" : [ ],
          "order" : 0.0,
          "active" : true
        }, {
          "name" : "No",
          "uuid" : "f88da2e8-6ab4-44b5-b762-233485cd25f9",
          "dataType" : "NA",
          "answers" : [ ],
          "order" : 1.0,
          "active" : true
        } ],
        "active" : true,
        "keyValues" : [ ]
      },
      "displayOrder" : 10.0,
      "type" : "SingleSelect",
      "mandatory" : true
    }, {
      "name" : "Disability",
      "uuid" : "4abfe22c-5589-4768-bb86-2e6f2812e8b5",
      "keyValues" : [ ],
      "concept" : {
        "name" : "Type of disability",
        "uuid" : "7061c675-c2ba-4016-886d-eeb432548378",
        "dataType" : "Coded",
        "answers" : [ {
          "name" : "Mental retardation",
          "uuid" : "7fb6744e-24c7-461f-9091-6c66156ebea0",
          "dataType" : "NA",
          "answers" : [ ],
          "order" : 11.0,
          "active" : true
        }, {
          "name" : "Post burn",
          "uuid" : "5b5fbb3d-1fe7-4711-bfce-77bbc465b832",
          "dataType" : "NA",
          "answers" : [ ],
          "order" : 6.0,
          "active" : true
        }, {
          "name" : "Arthritis",
          "uuid" : "6609670d-cd0e-414d-afde-af1d491d8b97",
          "dataType" : "NA",
          "answers" : [ ],
          "order" : 2.0,
          "active" : true
        }, {
          "name" : "Back pain",
          "uuid" : "33f8f979-d573-4aed-808f-e241dc53179f",
          "dataType" : "NA",
          "answers" : [ ],
          "order" : 3.0,
          "active" : true
        }, {
          "name" : "Post fracture",
          "uuid" : "17b4f868-4a61-4316-9338-4c458b0e45b5",
          "dataType" : "NA",
          "answers" : [ ],
          "order" : 5.0,
          "active" : true
        }, {
          "name" : "Cerebral Palsy",
          "uuid" : "33abbad1-4e96-4e80-951d-832607accfc5",
          "dataType" : "NA",
          "answers" : [ ],
          "order" : 1.0,
          "active" : true
        }, {
          "name" : "Paralysis",
          "uuid" : "c48b441b-5b7e-4c8c-9c6d-b91c3a7941fe",
          "dataType" : "NA",
          "answers" : [ ],
          "order" : 0.0,
          "active" : true
        }, {
          "name" : "Speech impairement",
          "uuid" : "301ec1f5-9d8e-4fbf-8f2b-f3c883457622",
          "dataType" : "NA",
          "answers" : [ ],
          "order" : 10.0,
          "active" : true
        }, {
          "name" : "Post operative",
          "uuid" : "9bcbb18e-b680-45bf-a6b5-d9d47e7cca1b",
          "dataType" : "NA",
          "answers" : [ ],
          "order" : 4.0,
          "active" : true
        }, {
          "name" : "Mental illness",
          "uuid" : "2c8705d4-b7f5-4d08-a515-cd8dbd4207d8",
          "dataType" : "NA",
          "answers" : [ ],
          "order" : 12.0,
          "active" : true
        }, {
          "name" : "Vision impairement",
          "uuid" : "18da1ae2-ec99-40dc-af1f-f6f86e5fc399",
          "dataType" : "NA",
          "answers" : [ ],
          "order" : 7.0,
          "active" : true
        }, {
          "name" : "Locomotor",
          "uuid" : "03e03f5d-4975-4d64-82fe-4c825cf1852c",
          "dataType" : "NA",
          "answers" : [ ],
          "order" : 9.0,
          "active" : true
        }, {
          "name" : "Hearing impairement",
          "uuid" : "d15dcefe-df9a-4bdc-9775-118bc57990ed",
          "dataType" : "NA",
          "answers" : [ ],
          "order" : 8.0,
          "active" : true
        } ],
        "active" : true,
        "keyValues" : [ ]
      },
      "displayOrder" : 11.0,
      "type" : "MultiSelect",
      "rule" : "'use strict';\n({params, imports}) => {\n  const individual = params.entity;\n  const formElement = params.formElement;\n  const statusBuilder = new imports.rulesConfig.FormElementStatusBuilder({individual, formElement});\n  statusBuilder.show().valueInRegistration(\"Whether any disability\").is.yes;\n  return statusBuilder.build();\n};",
      "mandatory" : true
    }, {
      "name" : "Disability",
      "uuid" : "7023387a-950d-4862-872e-11af66182147",
      "keyValues" : [ ],
      "concept" : {
        "name" : "Disability (voided~10316)",
        "uuid" : "eda07a4c-14c9-49af-b1d6-deaa695a5d36",
        "dataType" : "Text",
        "answers" : [ ],
        "active" : true,
        "voided" : true
      },
      "displayOrder" : 12.0,
      "type" : "SingleSelect",
      "rule" : "'use strict';\n({params, imports}) => {\n  const individual = params.entity;\n  const formElement = params.formElement;\n  const statusBuilder = new imports.rulesConfig.FormElementStatusBuilder({individual, formElement});\n  statusBuilder.show().valueInRegistration(\"Whether any disability\").is.yes;\n  return statusBuilder.build();\n};",
      "mandatory" : true,
      "voided" : true
    }, {
      "name" : "Religion",
      "uuid" : "71583e64-d2a0-4a9f-bc4f-2be063cb9ebe",
      "keyValues" : [ ],
      "concept" : {
        "name" : "Religion",
        "uuid" : "b2c60cb8-983c-4e0e-a90d-4b21e87e10bd",
        "dataType" : "Coded",
        "answers" : [ {
          "name" : "Hindu",
          "uuid" : "6dbd4a89-d040-4ed3-bf1d-23bafdb1553e",
          "dataType" : "NA",
          "answers" : [ ],
          "order" : 1.0,
          "active" : true
        }, {
          "name" : "Sikh",
          "uuid" : "2f6e7ba7-15dc-4af3-b4d7-e971e6733525",
          "dataType" : "NA",
          "answers" : [ ],
          "order" : 4.0,
          "active" : true
        }, {
          "name" : "Jain",
          "uuid" : "e8bb7929-2357-49ff-8c98-28b338f2c6d8",
          "dataType" : "NA",
          "answers" : [ ],
          "order" : 5.0,
          "active" : true
        }, {
          "name" : "Muslim",
          "uuid" : "fd46c9f7-783a-4cc0-b6b3-489aeb28f26c",
          "dataType" : "NA",
          "answers" : [ ],
          "order" : 2.0,
          "active" : true
        }, {
          "name" : "Christian",
          "uuid" : "a1a0ecc3-2a85-43c4-b75a-3544a1ada0bf",
          "dataType" : "NA",
          "answers" : [ ],
          "order" : 3.0,
          "active" : true
        }, {
          "name" : "Other",
          "uuid" : "798b7942-cf58-4d4e-a529-5972942e0a7e",
          "dataType" : "NA",
          "answers" : [ ],
          "order" : 6.0,
          "active" : true
        } ],
        "active" : true
      },
      "displayOrder" : 13.0,
      "type" : "SingleSelect",
      "mandatory" : true,
      "voided" : true
    }, {
      "name" : "Status of the individual",
      "uuid" : "e7f4a2cd-c984-4437-a2ce-120c102c0cca",
      "keyValues" : [ ],
      "concept" : {
        "name" : "Status of the individual",
        "uuid" : "d333f2a2-717e-478f-acbc-173bc7374d66",
        "dataType" : "Coded",
        "answers" : [ {
          "name" : "Out migrant",
          "uuid" : "e57e1f8d-0a6c-4470-b692-3dc82cce0dfc",
          "dataType" : "NA",
          "answers" : [ ],
          "order" : 4.0,
          "active" : true,
          "keyValues" : [ ]
        }, {
          "name" : "Birth",
          "uuid" : "a8a31361-df8c-4b6e-8075-639f436d0b3f",
          "dataType" : "NA",
          "answers" : [ ],
          "order" : 5.0,
          "active" : true
        }, {
          "name" : "Resident",
          "uuid" : "cc8a0f5e-be37-4e6a-8f49-41c9f7d2f839",
          "dataType" : "NA",
          "answers" : [ ],
          "order" : 0.0,
          "active" : true,
          "keyValues" : [ ]
        }, {
          "name" : "Death",
          "uuid" : "c125eec0-2bc4-4add-b1d0-7531e5ffa9c8",
          "dataType" : "NA",
          "answers" : [ ],
          "order" : 1.0,
          "active" : true
        }, {
          "name" : "Female marriage",
          "uuid" : "4d5e83b5-ddc3-4668-930f-96da0cce7763",
          "dataType" : "NA",
          "answers" : [ ],
          "order" : 2.0,
          "active" : true,
          "keyValues" : [ ]
        }, {
          "name" : "In migrant",
          "uuid" : "285a38f0-52a1-4021-90cc-3ba8cbe88371",
          "dataType" : "NA",
          "answers" : [ ],
          "order" : 3.0,
          "active" : true,
          "keyValues" : [ ]
        } ],
        "active" : true,
        "keyValues" : [ ]
      },
      "displayOrder" : 14.0,
      "type" : "SingleSelect",
      "mandatory" : true
    }, {
      "name" : "Aadhaar number",
      "uuid" : "114fe964-f3eb-4264-84a8-fd6822a25d8e",
      "keyValues" : [ ],
      "concept" : {
        "name" : "Aadhaar ID",
        "uuid" : "681fce2b-ea38-4651-a0b8-2cddd307ade7",
        "dataType" : "Numeric",
        "answers" : [ ],
        "active" : true
      },
      "displayOrder" : 15.0,
      "type" : "SingleSelect",
      "mandatory" : false
    }, {
      "name" : "Aadhaar ID",
      "uuid" : "82ae5f08-f53d-4b55-99f6-0bb7e290b28a",
      "keyValues" : [ ],
      "concept" : {
        "name" : "Aadhaar ID",
        "uuid" : "681fce2b-ea38-4651-a0b8-2cddd307ade7",
        "dataType" : "Numeric",
        "answers" : [ ],
        "active" : true
      },
      "displayOrder" : 16.0,
      "type" : "SingleSelect",
      "mandatory" : false,
      "voided" : true
    }, {
      "name" : "Contact Number",
      "uuid" : "270d44e9-6d3e-4613-a3fc-1d4798499e87",
      "keyValues" : [ ],
      "concept" : {
        "name" : "Contact Number",
        "uuid" : "0a725832-b21c-4151-b017-7e6af770ba54",
        "dataType" : "Text",
        "answers" : [ ],
        "active" : true
      },
      "displayOrder" : 17.0,
      "type" : "SingleSelect",
      "rule" : "",
      "mandatory" : false
    }, {
      "name" : "Smart card (Insurance)",
      "uuid" : "2b40ccb3-74aa-4b62-b9a9-7ad7a57b91c5",
      "keyValues" : [ ],
      "concept" : {
        "name" : "Smart card (Insurance)",
        "uuid" : "2a445ac8-56e7-4eda-8756-0a9c4fa9a77b",
        "dataType" : "Coded",
        "answers" : [ {
          "name" : "No",
          "uuid" : "f88da2e8-6ab4-44b5-b762-233485cd25f9",
          "dataType" : "NA",
          "answers" : [ ],
          "order" : 1.0,
          "active" : true
        }, {
          "name" : "Yes",
          "uuid" : "57e20de7-10de-4391-b7ce-87b2f40d19a2",
          "dataType" : "NA",
          "answers" : [ ],
          "order" : 0.0,
          "active" : true
        } ],
        "active" : true,
        "keyValues" : [ ]
      },
      "displayOrder" : 18.0,
      "type" : "SingleSelect",
      "mandatory" : false
    }, {
      "name" : "Electricity in house",
      "uuid" : "5cd59ef1-6749-446f-8f77-f9ec5bd3d594",
      "keyValues" : [ ],
      "concept" : {
        "name" : "Electricity in house",
        "uuid" : "e23ef639-5d54-46bc-811c-ee1886bce81f",
        "dataType" : "Coded",
        "answers" : [ {
          "name" : "No",
          "uuid" : "f88da2e8-6ab4-44b5-b762-233485cd25f9",
          "dataType" : "NA",
          "answers" : [ ],
          "order" : 1.0,
          "active" : true
        }, {
          "name" : "Yes",
          "uuid" : "57e20de7-10de-4391-b7ce-87b2f40d19a2",
          "dataType" : "NA",
          "answers" : [ ],
          "order" : 0.0,
          "active" : true
        } ],
        "active" : true,
        "keyValues" : [ ]
      },
      "displayOrder" : 19.0,
      "type" : "SingleSelect",
      "mandatory" : false,
      "voided" : true
    } ],
    "timed" : false
  }, {
    "uuid" : "53b260f8-a5a9-4062-a3f7-a117ade6daee",
    "name" : "Socio-Economic Details",
    "displayOrder" : 3.0,
    "display" : "Socio-Economic Details",
    "formElements" : [ {
      "name" : "Any owned land?",
      "uuid" : "d9b46945-9ba7-4525-9e0d-1e20eb7e88d6",
      "keyValues" : [ ],
      "concept" : {
        "name" : "Land possession",
        "uuid" : "b984ad33-05d8-4621-adf3-152e72a0db1b",
        "dataType" : "Coded",
        "answers" : [ {
          "name" : "No",
          "uuid" : "f88da2e8-6ab4-44b5-b762-233485cd25f9",
          "dataType" : "NA",
          "answers" : [ ],
          "order" : 2.0,
          "active" : true
        }, {
          "name" : "Yes",
          "uuid" : "57e20de7-10de-4391-b7ce-87b2f40d19a2",
          "dataType" : "NA",
          "answers" : [ ],
          "order" : 1.0,
          "active" : true
        } ],
        "active" : true
      },
      "displayOrder" : 1.0,
      "type" : "SingleSelect",
      "mandatory" : true,
      "voided" : true
    }, {
      "name" : "Land area",
      "uuid" : "9f7853d8-3976-4be0-8f4e-ba0cf6258678",
      "keyValues" : [ ],
      "concept" : {
        "name" : "Land Area",
        "uuid" : "430ebb19-831d-470d-80eb-7969814f13e4",
        "dataType" : "Numeric",
        "answers" : [ ],
        "active" : true
      },
      "displayOrder" : 2.0,
      "type" : "SingleSelect",
      "mandatory" : false,
      "voided" : true
    }, {
      "name" : "Type of residence",
      "uuid" : "8b624986-6f0d-4079-88ad-54ca75d66f17",
      "keyValues" : [ ],
      "concept" : {
        "name" : "Type of residence",
        "uuid" : "c5d2673b-0f5c-48bf-93e4-f1a1ae820732",
        "dataType" : "Coded",
        "answers" : [ {
          "name" : "Pakka",
          "uuid" : "bc43ce86-7cd4-474c-bced-8a5af0a4cb87",
          "dataType" : "NA",
          "answers" : [ ],
          "order" : 2.0,
          "active" : true
        }, {
          "name" : "Aadha kacha pakka",
          "uuid" : "7f731647-b8f8-4d5b-be2d-8d3ebd9cba05",
          "dataType" : "NA",
          "answers" : [ ],
          "order" : 3.0,
          "active" : true
        }, {
          "name" : "Kaccha",
          "uuid" : "65b3e4db-3c4e-4a56-9a2f-c07e9888e710",
          "dataType" : "NA",
          "answers" : [ ],
          "order" : 1.0,
          "active" : true
        } ],
        "active" : true
      },
      "displayOrder" : 3.0,
      "type" : "SingleSelect",
      "mandatory" : false,
      "voided" : true
    }, {
      "name" : "Economic Status",
      "uuid" : "f7b35aff-ca3d-4fa4-a8e0-ce532f51e0c3",
      "keyValues" : [ ],
      "concept" : {
        "name" : "Ration Card",
        "uuid" : "86fc3018-8eeb-4a58-a9d9-a40fff839305",
        "dataType" : "Coded",
        "answers" : [ {
          "name" : "No",
          "uuid" : "f88da2e8-6ab4-44b5-b762-233485cd25f9",
          "dataType" : "NA",
          "answers" : [ ],
          "order" : 4.0,
          "active" : true
        }, {
          "name" : "BPL",
          "uuid" : "906f6286-515b-4ff5-8065-0fcedef003b9",
          "dataType" : "NA",
          "answers" : [ ],
          "order" : 2.0,
          "active" : true
        }, {
          "name" : "APL",
          "uuid" : "3eac5822-f5fe-421d-8cdd-e89bef20baca",
          "dataType" : "NA",
          "answers" : [ ],
          "order" : 1.0,
          "active" : true
        }, {
          "name" : "Antyodaya",
          "uuid" : "78b4a024-82af-42fe-bf58-6da696073af9",
          "dataType" : "NA",
          "answers" : [ ],
          "order" : 3.0,
          "active" : true
        } ],
        "active" : true
      },
      "displayOrder" : 4.0,
      "type" : "SingleSelect",
      "mandatory" : false,
      "voided" : true
    }, {
      "name" : "Any property?",
      "uuid" : "bd4e6595-12c8-4667-9abb-c254dcfbd396",
      "keyValues" : [ ],
      "concept" : {
        "name" : "Property",
        "uuid" : "aa88dba4-4f5d-4d35-9dc1-2390969cc5f3",
        "dataType" : "Coded",
        "answers" : [ {
          "name" : "Tractor",
          "uuid" : "345821de-b302-4df3-9754-c555dfa530a3",
          "dataType" : "NA",
          "answers" : [ ],
          "order" : 1.0,
          "active" : true
        }, {
          "name" : "2 Wheeler",
          "uuid" : "03c61006-8dc8-449e-9486-ecfba3e84f99",
          "dataType" : "NA",
          "answers" : [ ],
          "order" : 3.0,
          "active" : true
        }, {
          "name" : "Other",
          "uuid" : "798b7942-cf58-4d4e-a529-5972942e0a7e",
          "dataType" : "NA",
          "answers" : [ ],
          "order" : 7.0,
          "active" : true
        }, {
          "name" : "Generator",
          "uuid" : "94099e11-6e9e-4c9e-9a68-83dee9d6042a",
          "dataType" : "NA",
          "answers" : [ ],
          "order" : 6.0,
          "active" : true
        }, {
          "name" : "Cycle",
          "uuid" : "12ee51fa-d8a5-4c8d-b88a-3a9c2f0dfaf1",
          "dataType" : "NA",
          "answers" : [ ],
          "order" : 5.0,
          "active" : true
        }, {
          "name" : "None",
          "uuid" : "8b77f487-c885-4b54-8925-153733913b10",
          "dataType" : "NA",
          "answers" : [ ],
          "order" : 8.0,
          "unique" : true,
          "active" : true
        }, {
          "name" : "4 Wheeler",
          "uuid" : "ad8156fd-c3ac-461c-8611-a5cf4cfbcc7e",
          "dataType" : "NA",
          "answers" : [ ],
          "order" : 2.0,
          "active" : true
        }, {
          "name" : "Fridge",
          "uuid" : "3b4d35f0-ef97-4954-8ee2-69d5db4894e6",
          "dataType" : "NA",
          "answers" : [ ],
          "order" : 4.0,
          "active" : true
        } ],
        "active" : true
      },
      "displayOrder" : 5.0,
      "type" : "MultiSelect",
      "mandatory" : true,
      "voided" : true
    }, {
      "name" : "Other property (please specify)",
      "uuid" : "78fac891-e4a4-4f9c-a139-bfa212b73ace",
      "keyValues" : [ ],
      "concept" : {
        "name" : "Other property",
        "uuid" : "32609e0f-f3c8-4dcb-af7c-5e8a96e8e89d",
        "dataType" : "Text",
        "answers" : [ ],
        "active" : true
      },
      "displayOrder" : 6.0,
      "type" : "SingleSelect",
      "mandatory" : true,
      "voided" : true
    } ],
    "voided" : true,
    "timed" : false
  } ],
  "decisionRule" : "",
  "visitScheduleRule" : "",
  "validationRule" : "",
  "checklistsRule" : "",
  "decisionConcepts" : [ ]
}